django-tiny-util/__init__.py
django_tiny_util/__init__.py
django_tiny_util/models.py
djangotinyutil/__init__.py
djangotinyutil/models.py
django_tiny_util-0.3.1.dist-info/LICENSE
django_tiny_util-0.3.1.dist-info/METADATA
django_tiny_util-0.3.1.dist-info/WHEEL
django_tiny_util-0.3.1.dist-info/top_level.txt
django_tiny_util-0.3.1.dist-info/RECORD
